aoc/__init__.py
aoc/bench.py
aoc/bind.py
aoc/cache.py
aoc/clear.py
aoc/cli.py
aoc/configuration.py
aoc/constants.py
aoc/context.py
aoc/input.py
aoc/load.py
aoc/misc.py
aoc/run.py
aoc/submit.py
aoc/test.py
aoc/timed_runner.py
aoc/timer.py
aoc/timing_context.py
aocenv-0.2.2.dist-info/METADATA
aocenv-0.2.2.dist-info/WHEEL
aocenv-0.2.2.dist-info/entry_points.txt
aocenv-0.2.2.dist-info/licenses/LICENSE
aocenv-0.2.2.dist-info/RECORD
