Metadata-Version: 2.4
Name: aocenv
Version: 0.2.2
Summary: User-friendly environment management CLI and package for Advent of Code
Project-URL: Homepage, https://github.com/Apsurt/aocenv
Project-URL: Repository, https://github.com/Apsurt/aocenv
Project-URL: Issues, https://github.com/Apsurt/aocenv/issues
Author-email: Tymon Becella <tymon.becella@gmail.com>
License-File: LICENSE
Keywords: advent-of-code,aoc,cli
Classifier: Development Status :: 3 - Alpha
Classifier: Intended Audience :: Developers
Classifier: License :: OSI Approved :: MIT License
Classifier: Operating System :: Unix
Classifier: Programming Language :: Python :: 3
Classifier: Programming Language :: Python :: 3.12
Classifier: Topic :: Games/Entertainment :: Puzzle Games
Classifier: Topic :: Software Development :: Libraries
Classifier: Topic :: Software Development :: Libraries :: Python Modules
Classifier: Topic :: System :: Filesystems
Classifier: Typing :: Typed
Requires-Python: >=3.12
Requires-Dist: beautifulsoup4
Requires-Dist: click
Requires-Dist: requests
Requires-Dist: rich
Requires-Dist: tqdm>=4.67.1
Requires-Dist: types-tqdm>=4.67.0.20250809
